{
  "name": "Tree Top",
  "shortName": "Tree Top",
  "bkColor": "00",
  "borderColor": "06",
  "layout": [
    "0000000000000000",
    "0000000000000000",
    "0000000000000000",
    "0000000000000000",
    "0000000000000000",
    "0000000000000000",
    "0000000040000000",
    "0000540000000000",
    "0000001400040000",
    "0150000014000000",
    "0000000000000000",
    "0000000000140000",
    "5555540008000000",
    "0CF3C81008005000",
    "CF3F080008500000",
    "3030080058000000"
  ],
  "graphicData": {
    "floor": "04AA55AA5830101008",
    "wall": "16A52852555549A2B5",
    "nasty": "42894A123418345291",
    "item": "1E2D377B6D5EB8C0",
    "ramp": {
      "data": "074000100004000100",
      "gradient": "left",
      "location": {"x": 15, "y": 14},
       "length": "02"
    }
  },
   "willy":{
      "init":{
         "x":134,
         "y":104,
         "direction":1,
         "frame":3
      }
   },
  "adjoiningRoom": {
    "left": "0D",
    "right": false,
    "above": false,
    "below": "08"
  },
   "guardians":{
      "horizontal":[
         {
            "figures":[
               {
                  "attribute":"45",
                  "limits":{
                     "left":0,
                     "right":86
                  },
                  "speed":0,
                  "init":{
                     "x":56,
                     "y":40,
                     "direction":1,
                     "frame":0
                  }
               }
            ],
            "width":12,
            "height":16,
            "paintCorrections":{
               "x":0,
               "y":0
            },
            "frames":4,
            "directions":2,
            "sprite":[
               [
                  "-----------",
                  "-----------",
                  "-----------",
                  "-----------",
                  "-----------",
                  "#-####-----",
                  "-######-##-",
                  "###-#-###-#",
                  "-#-#-##-##-",
                  "--#-#------",
                  "---#-#-----",
                  "--#-#------",
                  "-#-#-------",
                  "-----------",
                  "-----------",
                  "-----------"
               ],
               [
                  "------------",
                  "------------",
                  "------------",
                  "------------",
                  "------------",
                  "#-####------",
                  "-###-##--##-",
                  "#-#-#-####-#",
                  "-#-#-##--##-",
                  "--#-#-------",
                  "-#----------",
                  "------------",
                  "------------",
                  "------------",
                  "------------",
                  "------------"
               ],
               [
                  "------------",
                  "------------",
                  "-#-#--------",
                  "--#-#-------",
                  "---#-#------",
                  "#-#-#-------",
                  "-#-#-##-##--",
                  "###-#-###-#-",
                  "-######-##--",
                  "--####------",
                  "------------",
                  "------------",
                  "------------",
                  "------------",
                  "------------",
                  "------------"
               ],
               [
                  "------------",
                  "------------",
                  "------------",
                  "------------",
                  "------------",
                  "#-####-##---",
                  "-###-###-#--",
                  "#-#-#-###---",
                  "-#-#-##-----",
                  "--#-#-------",
                  "-#----------",
                  "------------",
                  "------------",
                  "------------",
                  "------------",
                  "------------"
               ],
               [
                  "------------",
                  "------------",
                  "------------",
                  "------------",
                  "------------",
                  "---##-####-#",
                  "--#-###-###-",
                  "---###-#-#-#",
                  "-----##-#-#-",
                  "-------#-#--",
                  "----------#-",
                  "------------",
                  "------------",
                  "------------",
                  "------------",
                  "------------"
               ],
               [
                  "-------------",
                  "-------------",
                  "---------#-#-",
                  "--------#-#--",
                  "-------#-#---",
                  "--------#-#-#",
                  "---##-##-#-#-",
                  "--#-###-#-###",
                  "---##-######-",
                  "-------####--",
                  "-------------",
                  "-------------",
                  "-------------",
                  "-------------",
                  "-------------",
                  "-------------"
               ],
               [
                  "------------",
                  "------------",
                  "------------",
                  "------------",
                  "------------",
                  "------####-#",
                  "-##--##-###-",
                  "#-####-#-#-#",
                  "-##--##-#-#-",
                  "-------#-#--",
                  "----------#-",
                  "------------",
                  "------------",
                  "------------",
                  "------------",
                  "------------"
               ],
               [
                  "------------",
                  "------------",
                  "------------",
                  "------------",
                  "------------",
                  "------####-#",
                  "--##-######-",
                  "-#-###-#-###",
                  "--##-##-#-#-",
                  "-------#-#--",
                  "------#-#---",
                  "-------#-#--",
                  "--------#-#-",
                  "------------",
                  "------------",
                  "------------"
               ]
            ],
            "mapSprite": [
               "----",
               "##--",
               "####",
               "----"
            ]
         },
         {
            "figures":[
               {
                  "attribute":"06",
                  "limits":{
                     "left":0,
                     "right":158
                  },
                  "speed":0,
                  "init":{
                     "x":64,
                     "y":80,
                     "direction":1,
                     "frame":0
                  }
               }
            ],
            "width":11,
            "height":16,
            "paintCorrections":{
               "x":-1,
               "y":0
            },
            "frames":4,
            "directions":1,
            "sprite":[
              [
                "------#-----",
                "---#-#-#-#--",
                "--#-#-#-#-#-",
                "---#-#-###--",
                "--#---#---#-",
                "-#-#-#####-#",
                "--#-#####-#-",
                "---#-----#--",
                "--#-#-#-#-#-",
                "---#-#-#-#--",
                "------#-----",
                "------#-----",
                "-----#------",
                "---#####----",
                "--#-----#---",
                "-#------#---"
              ],
              [
                "-----#-----",
                "--#-#-#-#--",
                "-#-#-#-#-#-",
                "--#-#-###--",
                "-#---#---#-",
                "#-#####-#-#",
                "-#-#-#-#-#-",
                "--#-----#--",
                "-#-#-#-#-#-",
                "--#-#-#-#--",
                "-----#-----",
                "-----#-----",
                "---###-----",
                "--#---##---",
                "-#------#--",
                "-----------"
              ],
              [
                "-----#-----",
                "--#-#-#-#--",
                "-#-#-#-#-#-",
                "--###-#-#--",
                "-#---#---#-",
                "#-#####-#-#",
                "-#-#####-#-",
                "--#-----#--",
                "-#-#-#-#-#-",
                "--#-#-#-#--",
                "-----#-----",
                "-----#-----",
                "-----###---",
                "---##---#--",
                "--#------#-",
                "-----------"
              ],
              [
                "-----#-----",
                "--#-#-#-#--",
                "-#-#-#-#-#-",
                "--###-#-#--",
                "-#---#---#-",
                "#-#-#####-#",
                "-#-#####-#-",
                "--#-#-#-#--",
                "-#-#-#-#-#-",
                "--#-#-#-#--",
                "-----#-----",
                "-----#-----",
                "------#----",
                "----#####--",
                "---#-----#-",
                "---#------#"
              ]
            ],
            "mapSprite": [
               "###",
               "###",
               "-#-",
               "###"
            ]
         },
         {
            "figures":[
               {
                  "attribute":"42",
                  "limits":{
                     "left":40,
                     "right":246
                  },
                  "speed":0,
                  "init":{
                     "x":192,
                     "y":24,
                     "direction":1,
                     "frame":0
                  }
               }
            ],
            "width":10,
            "height":16,
            "paintCorrections":{
               "x":-2,
               "y":0
            },
            "frames":4,
            "directions":2,
            "sprite":[
              [
                "--#---------",
                "---#-#------",
                "--#-#-#-----",
                "---#-#------",
                "--#-#-#-----",
                "--##-#-#-#--",
                "---##-#-#---",
                "--##-#-###--",
                "--#-#-#-#-#-",
                "--##-#-#####",
                "--##########",
                "---######---",
                "---#---#----",
                "---#---#----",
                "------------",
                "------------"
              ],
              [
                "------------",
                "------------",
                "------------",
                "------------",
                "------------",
                "--#-##---#--",
                "---####-#---",
                "--########--",
                "--#-#-#-#-#-",
                "-#-#-#-#####",
                "--#-#-######",
                "-#-######---",
                "---#---#----",
                "--#-----#---",
                "------------",
                "------------"
              ],
              [
                "------------",
                "------------",
                "------------",
                "------------",
                "------------",
                "--#-##---#--",
                "---####-#---",
                "--########--",
                "--##-#-##-#-",
                "--#-#-#-####",
                "-#-#-#-#####",
                "--#-#-###---",
                "-#-#-#-#----",
                "#-#-#--#----",
                "-#-#--------",
                "#-#---------"
              ],
              [
                "------------",
                "------------",
                "------------",
                "------------",
                "------------",
                "--#-##--#---",
                "---####-#---",
                "--########--",
                "--#-#-#-#-#-",
                "-#-#-#-#####",
                "--#-#-######",
                "-#-######---",
                "---#---#----",
                "----#-#-----",
                "------------",
                "------------"
              ],
              [
                "--------------",
                "--------------",
                "--------------",
                "--------------",
                "--------------",
                "-----#--##-#--",
                "-----#-####---",
                "----########--",
                "---#-#-#-#-#--",
                "--#####-#-#-#-",
                "--######-#-#--",
                "-----######-#-",
                "------#---#---",
                "-------#-#----",
                "--------------",
                "--------------"
              ],
              [
                "--------------",
                "--------------",
                "--------------",
                "--------------",
                "--------------",
                "----#---##-#--",
                "-----#-####---",
                "----########--",
                "---#-##-#-##--",
                "--####-#-#-#--",
                "--#####-#-#-#-",
                "-----###-#-#--",
                "------#-#-#-#-",
                "------#--#-#-#",
                "----------#-#-",
                "-----------#-#"
              ],
              [
                "--------------",
                "--------------",
                "--------------",
                "--------------",
                "--------------",
                "----#---##-#--",
                "-----#-####---",
                "----########--",
                "---#-#-#-#-#--",
                "--#####-#-#-#-",
                "--######-#-#--",
                "-----######-#-",
                "------#---#---",
                "-----#-----#--",
                "--------------",
                "--------------"
              ],
              [
                "----------##--",
                "--------#-#---",
                "-------#-#-#--",
                "--------#-#---",
                "-------#-#-#--",
                "----#-#-#-##--",
                "-----#-#-##---",
                "----###-#-##--",
                "---#-#-#-#-#--",
                "--#####-#-##--",
                "--##########--",
                "-----######---",
                "------#---#---",
                "------#---#---",
                "--------------",
                "--------------"
              ]
            ],
            "mapSprite": [
               "##--",
               "###-",
               "####",
               "#-#-"
            ]
         }
      ],
      "arrow":[
         {
            "figures":[
               {
                  "attribute":"07",
                  "minCounter":0,
                  "maxCounter":255,
                  "soundWhenCounter":44,
                  "speed":8,
                  "init":{
                     "x":224,
                     "y":66,
                     "hide":false,
                     "counter":28,
                     "direction":1,
                     "frame":0
                  }
               }
            ],
            "width":8,
            "height":2,
            "paintCorrections":{
               "x":0,
               "y":-1
            },
            "frames":1,
            "directions":1,
            "sprite":[
               [
                  "-#-----#",
                  "########",
                  "-#-----#"
               ]
            ]
         }
      ]
   }
}